gapic/cli/__init__.py
gapic/cli/dump.py
gapic/cli/generate.py
gapic/cli/generate_with_pandoc.py
gapic/configurable_snippetgen/__init__.py
gapic/configurable_snippetgen/configured_snippet.py
gapic/configurable_snippetgen/libcst_utils.py
gapic/configurable_snippetgen/snippet_config_language.proto
gapic/configurable_snippetgen/snippet_config_language_pb2.py
gapic/configurable_snippetgen/snippet_config_language_pb2.pyi
gapic/generator/__init__.py
gapic/generator/formatter.py
gapic/generator/generator.py
gapic/samplegen/__init__.py
gapic/samplegen/manifest.py
gapic/samplegen/samplegen.py
gapic/samplegen_utils/__init__.py
gapic/samplegen_utils/snippet_index.py
gapic/samplegen_utils/snippet_metadata.proto
gapic/samplegen_utils/snippet_metadata_pb2.py
gapic/samplegen_utils/types.py
gapic/samplegen_utils/utils.py
gapic/samplegen_utils/yaml.py
gapic/schema/__init__.py
gapic/schema/api.py
gapic/schema/imp.py
gapic/schema/metadata.py
gapic/schema/mixins.py
gapic/schema/naming.py
gapic/schema/wrappers.py
gapic/templates/.coveragerc.j2
gapic/templates/.flake8.j2
gapic/templates/LICENSE.j2
gapic/templates/MANIFEST.in.j2
gapic/templates/README.rst.j2
gapic/templates/_base.py.j2
gapic/templates/_license.j2
gapic/templates/_pypi_packages.j2
gapic/templates/mypy.ini.j2
gapic/templates/noxfile.py.j2
gapic/templates/setup.py.j2
gapic/templates/%namespace/%name/__init__.py.j2
gapic/templates/%namespace/%name/gapic_version.py.j2
gapic/templates/%namespace/%name/py.typed.j2
gapic/templates/%namespace/%name_%version/gapic_metadata.json.j2
gapic/templates/%namespace/%name_%version/gapic_version.py.j2
gapic/templates/%namespace/%name_%version/py.typed.j2
gapic/templates/%namespace/%name_%version/%sub/__init__.py.j2
gapic/templates/%namespace/%name_%version/%sub/services/__init__.py.j2
gapic/templates/%namespace/%name_%version/%sub/services/%service/__init__.py.j2
gapic/templates/%namespace/%name_%version/%sub/services/%service/_async_mixins.py.j2
gapic_generator-1.30.5.dist-info/licenses/LICENSE
gapic_generator-1.30.5.dist-info/METADATA
gapic_generator-1.30.5.dist-info/WHEEL
gapic_generator-1.30.5.dist-info/entry_points.txt
gapic_generator-1.30.5.dist-info/top_level.txt
gapic_generator-1.30.5.dist-info/RECORD
